<?xml version="1.0" encoding="utf-8"?>
<Dependencies>
  <ProductDependencies>
  </ProductDependencies>
  <ToolsetDependencies>
    <Dependency Name="Microsoft.DotNet.Arcade.Sdk" Version="8.0.0-beta.23558.2">
      <Uri>https://github.com/dotnet/arcade</Uri>
      <Sha>174b6d459807420d44f6c5e49f3d47e44892f1c1</Sha>
    </Dependency>
    <Dependency Name="Microsoft.DotNet.Helix.Sdk" Version="8.0.0-beta.23558.2">
      <Uri>https://github.com/dotnet/arcade</Uri>
      <Sha>174b6d459807420d44f6c5e49f3d47e44892f1c1</Sha>
    </Dependency>
  </ToolsetDependencies>
</Dependencies>
