<?xml version="1.0" encoding="utf-8"?>
<Dependencies>
  <ProductDependencies>
  </ProductDependencies>
  <ToolsetDependencies>
    <Dependency Name="Microsoft.DotNet.Arcade.Sdk" Version="6.0.0-beta.21256.9">
      <Uri>https://github.com/dotnet/arcade</Uri>
      <Sha>3094203c203fdbd77c2ba43578a1a8f92e1b467d</Sha>
    </Dependency>
    <Dependency Name="Microsoft.DotNet.Helix.Sdk" Version="6.0.0-beta.21256.9">
      <Uri>https://github.com/dotnet/arcade</Uri>
      <Sha>3094203c203fdbd77c2ba43578a1a8f92e1b467d</Sha>
    </Dependency>
  </ToolsetDependencies>
</Dependencies>
