<?xml version="1.0" encoding="utf-8"?>
<Dependencies>
  <ProductDependencies>
  </ProductDependencies>
  <ToolsetDependencies>
    <Dependency Name="Microsoft.DotNet.Arcade.Sdk" Version="5.0.0-beta.20263.8">
      <Uri>https://github.com/dotnet/arcade</Uri>
      <Sha>9564dff88ac7e42e27befeb44253c646fe2f5fbe</Sha>
    </Dependency>
    <Dependency Name="Microsoft.DotNet.Helix.Sdk" Version="5.0.0-beta.20263.8">
      <Uri>https://github.com/dotnet/arcade</Uri>
      <Sha>9564dff88ac7e42e27befeb44253c646fe2f5fbe</Sha>
    </Dependency>
  </ToolsetDependencies>
</Dependencies>
