<?xml version="1.0" encoding="utf-8"?>
<Dependencies>
  <ProductDependencies></ProductDependencies>
  <ToolsetDependencies>
    <Dependency Name="Microsoft.DotNet.Arcade.Sdk" Version="1.0.0-beta.19074.7">
      <Uri>https://github.com/dotnet/arcade</Uri>
      <Sha>8c523945d34e8a0e62ea1a9a76e1ced9ed760b04</Sha>
    </Dependency>
    <Dependency Name="Microsoft.DotNet.Helix.Sdk" Version="2.0.0-beta.19074.7">
      <Uri>https://github.com/dotnet/arcade</Uri>
      <Sha>8c523945d34e8a0e62ea1a9a76e1ced9ed760b04</Sha>
    </Dependency>
  </ToolsetDependencies>
</Dependencies>
