<?xml version="1.0" encoding="utf-8"?>
<Dependencies>
  <ProductDependencies>
  </ProductDependencies>
  <ToolsetDependencies>
    <Dependency Name="Microsoft.DotNet.Arcade.Sdk" Version="10.0.0-beta.25103.2">
      <Uri>https://github.com/dotnet/arcade</Uri>
      <Sha>a66d0239958d2ccebf4eb1175452c1e6ea7bbe86</Sha>
    </Dependency>
    <Dependency Name="Microsoft.DotNet.Helix.Sdk" Version="10.0.0-beta.25103.2">
      <Uri>https://github.com/dotnet/arcade</Uri>
      <Sha>a66d0239958d2ccebf4eb1175452c1e6ea7bbe86</Sha>
    </Dependency>
    <Dependency Name="Microsoft.SourceBuild.Intermediate.arcade" Version="10.0.0-beta.25103.2">
      <Uri>https://github.com/dotnet/arcade</Uri>
      <Sha>a66d0239958d2ccebf4eb1175452c1e6ea7bbe86</Sha>
      <SourceBuild RepoName="arcade" ManagedOnly="true" />
    </Dependency>
  </ToolsetDependencies>
</Dependencies>
