<?xml version="1.0" encoding="utf-8"?>
<Dependencies>
  <ProductDependencies>
  </ProductDependencies>
  <ToolsetDependencies>
    <Dependency Name="Microsoft.DotNet.Arcade.Sdk" Version="7.0.0-beta.22376.2">
      <Uri>https://github.com/dotnet/arcade</Uri>
      <Sha>6543f361aea752f2180112e2a9e72971e9fa9ba8</Sha>
    </Dependency>
    <Dependency Name="Microsoft.DotNet.Helix.Sdk" Version="7.0.0-beta.22376.2">
      <Uri>https://github.com/dotnet/arcade</Uri>
      <Sha>6543f361aea752f2180112e2a9e72971e9fa9ba8</Sha>
    </Dependency>
  </ToolsetDependencies>
</Dependencies>
