<?xml version="1.0" encoding="utf-8"?>
<Dependencies>
  <ProductDependencies>
  </ProductDependencies>
  <ToolsetDependencies>
    <Dependency Name="Microsoft.DotNet.Arcade.Sdk" Version="1.0.0-beta.19416.10">
      <Uri>https://github.com/dotnet/arcade</Uri>
      <Sha>762860fbcd9761c0a89692262987d645aa0a29b5</Sha>
    </Dependency>
    <Dependency Name="Microsoft.DotNet.Helix.Sdk" Version="2.0.0-beta.19416.10">
      <Uri>https://github.com/dotnet/arcade</Uri>
      <Sha>762860fbcd9761c0a89692262987d645aa0a29b5</Sha>
    </Dependency>
  </ToolsetDependencies>
</Dependencies>
